epnurbs/__init__.py
epnurbs/createnurbsopening.py
epnurbs/createnurbsshading.py
epnurbs/createrectshading.py
epnurbs/helper_methods.py
epnurbs-1.0.2a1.dist-info/METADATA
epnurbs-1.0.2a1.dist-info/RECORD
epnurbs-1.0.2a1.dist-info/WHEEL
epnurbs-1.0.2a1.dist-info/top_level.txt
